LICENSE
MANIFEST.in
README.md
README.rst
RELNOTES.md
commands.py
setup.cfg
setup.py
version.py
docs/Makefile
docs/advanced.rst
docs/bucket.rst
docs/client.rst
docs/conf.py
docs/datatypes.rst
docs/index.rst
docs/make.bat
docs/object.rst
docs/query.rst
docs/security.rst
riak/__init__.py
riak/benchmark.py
riak/bucket.py
riak/content.py
riak/mapreduce.py
riak/multidict.py
riak/node.py
riak/resolver.py
riak/riak_error.py
riak/riak_object.py
riak/security.py
riak/table.py
riak/test_server.py
riak/ts_object.py
riak/tz.py
riak/util.py
riak.egg-info/PKG-INFO
riak.egg-info/SOURCES.txt
riak.egg-info/dependency_links.txt
riak.egg-info/requires.txt
riak.egg-info/top_level.txt
riak.egg-info/zip-safe
riak/client/__init__.py
riak/client/index_page.py
riak/client/multi.py
riak/client/operations.py
riak/client/transport.py
riak/codecs/__init__.py
riak/codecs/http.py
riak/codecs/pbuf.py
riak/codecs/ttb.py
riak/codecs/util.py
riak/datatypes/__init__.py
riak/datatypes/counter.py
riak/datatypes/datatype.py
riak/datatypes/errors.py
riak/datatypes/flag.py
riak/datatypes/hll.py
riak/datatypes/map.py
riak/datatypes/register.py
riak/datatypes/set.py
riak/datatypes/types.py
riak/erl_src/riak_kv_test_backend.beam
riak/erl_src/riak_kv_test_backend.erl
riak/erl_src/riak_search_test_backend.beam
riak/erl_src/riak_search_test_backend.erl
riak/pb/__init__.py
riak/pb/messages.py
riak/pb/riak_dt_pb2.py
riak/pb/riak_kv_pb2.py
riak/pb/riak_pb2.py
riak/pb/riak_search_pb2.py
riak/pb/riak_ts_pb2.py
riak/pb/riak_yokozuna_pb2.py
riak/tests/__init__.py
riak/tests/base.py
riak/tests/comparison.py
riak/tests/pool-grinder.py
riak/tests/suite.py
riak/tests/test_2i.py
riak/tests/test_btypes.py
riak/tests/test_client.py
riak/tests/test_comparison.py
riak/tests/test_datatypes.py
riak/tests/test_datetime.py
riak/tests/test_feature_detection.py
riak/tests/test_filters.py
riak/tests/test_kv.py
riak/tests/test_mapreduce.py
riak/tests/test_misc.py
riak/tests/test_pool.py
riak/tests/test_search.py
riak/tests/test_security.py
riak/tests/test_server_test.py
riak/tests/test_timeseries_pbuf.py
riak/tests/test_timeseries_ttb.py
riak/tests/test_util.py
riak/tests/test_yokozuna.py
